Workbook

Sheet Daily Route Record
A1: Departure Date | B1: Return Date | C1: Trip Days | D1: Route | E1: Diesel Expense | F1: Oil Expense | G1: Ration / Food Expense | H1: Mobile Expense | I1: Misc Expense | J1: Driver Salary | K1: Garage Expense | L1: Service Expense | M1: Total Expenses | N1: Income 1 | O1: Income 2 | P1: Income 3 | Q1: Income 4 | R1: Total Income | S1: Additional Expense Detail | T1: Additional Expense Amount | U1: Profit | V1: Loss
C2: =IF(AND(A2<>"",B2<>""),IFERROR((IF(ISNUMBER(B2),B2,DATE(VALUE(RIGHT(B2,LEN(B2)-FIND("/",B2,FIND("/",B2)+1))),VALUE(MID(B2,FIND("/",B2)+1,FIND("/",B2,FIND("/",B2)+1)-FIND("/",B2)-1)),VALUE(LEFT(B2,FIND("/",B2)-1)))))-(IF(ISNUMBER(A2),A2,DATE(VALUE(RIGHT(A2,LEN(A2)-FIND("/",A2,FIND("/",A2)+1))),VALUE(MID(A2,FIND("/",A2)+1,FIND("/",A2,FIND("/",A2)+1)-FIND("/",A2)-1)),VALUE(LEFT(A2,FIND("/",A2)-1))))),""),"") | M2: =SUM(E2:L2) | R2: =SUM(N2:Q2) | U2: =MAX(R2-(M2+T2),0) | V2: =MAX((M2+T2)-R2,0)
A3: Type date as dd/mm/yyyy | B3: Type date as dd/mm/yyyy

Sheet Monthly Summary
A1: Year | B1: Month No | C1: Month Name | D1: Trips | E1: Total Expenses | F1: Total Income | G1: Additional Expenses | H1: Profit | I1: Loss
A2: =YEAR(TODAY()) | B2: 1 | C2: =TEXT(DATE(A2,B2,1),"mmmm") | D2: =SUMPRODUCT((IFERROR(--RIGHT(DailyRouteRecordTable[Departure Date],4),0)=A2)*(IFERROR(--MID(DailyRouteRecordTable[Departure Date],4,2),0)=B2)) | E2: =SUMPRODUCT((IFERROR(--RIGHT(DailyRouteRecordTable[Departure Date],4),0)=A2)*(IFERROR(--MID(DailyRouteRecordTable[Departure Date],4,2),0)=B2)*N(DailyRouteRecordTable[Total Expenses])) | F2: =SUMPRODUCT((IFERROR(--RIGHT(DailyRouteRecordTable[Departure Date],4),0)=A2)*(IFERROR(--MID(DailyRouteRecordTable[Departure Date],4,2),0)=B2)*N(DailyRouteRecordTable[Total Income])) | G2: =SUMPRODUCT((IFERROR(--RIGHT(DailyRouteRecordTable[Departure Date],4),0)=A2)*(IFERROR(--MID(DailyRouteRecordTable[Departure Date],4,2),0)=B2)*N(DailyRouteRecordTable[Additional Expense Amount])) | H2: =MAX(F2-(E2+G2),0) | I2: =MAX((E2+G2)-F2,0)
A3: =YEAR(TODAY()) | B3: 2 | C3: =TEXT(DATE(A3,B3,1),"mmmm") | D3: =SUMPRODUCT((IFERROR(--RIGHT(DailyRouteRecordTable[Departure Date],4),0)=A3)*(IFERROR(--MID(DailyRouteRecordTable[Departure Date],4,2),0)=B3)) | E3: =SUMPRODUCT((IFERROR(--RIGHT(DailyRouteRecordTable[Departure Date],4),0)=A3)*(IFERROR(--MID(DailyRouteRecordTable[Departure Date],4,2),0)=B3)*N(DailyRouteRecordTable[Total Expenses])) | F3: =SUMPRODUCT((IFERROR(--RIGHT(DailyRouteRecordTable[Departure Date],4),0)=A3)*(IFERROR(--MID(DailyRouteRecordTable[Departure Date],4,2),0)=B3)*N(DailyRouteRecordTable[Total Income])) | G3: =SUMPRODUCT((IFERROR(--RIGHT(DailyRouteRecordTable[Departure Date],4),0)=A3)*(IFERROR(--MID(DailyRouteRecordTable[Departure Date],4,2),0)=B3)*N(DailyRouteRecordTable[Additional Expense Amount])) | H3: =MAX(F3-(E3+G3),0) | I3: =MAX((E3+G3)-F3,0)
A4: =YEAR(TODAY()) | B4: 3 | C4: =TEXT(DATE(A4,B4,1),"mmmm") | D4: =SUMPRODUCT((IFERROR(--RIGHT(DailyRouteRecordTable[Departure Date],4),0)=A4)*(IFERROR(--MID(DailyRouteRecordTable[Departure Date],4,2),0)=B4)) | E4: =SUMPRODUCT((IFERROR(--RIGHT(DailyRouteRecordTable[Departure Date],4),0)=A4)*(IFERROR(--MID(DailyRouteRecordTable[Departure Date],4,2),0)=B4)*N(DailyRouteRecordTable[Total Expenses])) | F4: =SUMPRODUCT((IFERROR(--RIGHT(DailyRouteRecordTable[Departure Date],4),0)=A4)*(IFERROR(--MID(DailyRouteRecordTable[Departure Date],4,2),0)=B4)*N(DailyRouteRecordTable[Total Income])) | G4: =SUMPRODUCT((IFERROR(--RIGHT(DailyRouteRecordTable[Departure Date],4),0)=A4)*(IFERROR(--MID(DailyRouteRecordTable[Departure Date],4,2),0)=B4)*N(DailyRouteRecordTable[Additional Expense Amount])) | H4: =MAX(F4-(E4+G4),0) | I4: =MAX((E4+G4)-F4,0)
A5: =YEAR(TODAY()) | B5: 4 | C5: =TEXT(DATE(A5,B5,1),"mmmm") | D5: =SUMPRODUCT((IFERROR(--RIGHT(DailyRouteRecordTable[Departure Date],4),0)=A5)*(IFERROR(--MID(DailyRouteRecordTable[Departure Date],4,2),0)=B5)) | E5: =SUMPRODUCT((IFERROR(--RIGHT(DailyRouteRecordTable[Departure Date],4),0)=A5)*(IFERROR(--MID(DailyRouteRecordTable[Departure Date],4,2),0)=B5)*N(DailyRouteRecordTable[Total Expenses])) | F5: =SUMPRODUCT((IFERROR(--RIGHT(DailyRouteRecordTable[Departure Date],4),0)=A5)*(IFERROR(--MID(DailyRouteRecordTable[Departure Date],4,2),0)=B5)*N(DailyRouteRecordTable[Total Income])) | G5: =SUMPRODUCT((IFERROR(--RIGHT(DailyRouteRecordTable[Departure Date],4),0)=A5)*(IFERROR(--MID(DailyRouteRecordTable[Departure Date],4,2),0)=B5)*N(DailyRouteRecordTable[Additional Expense Amount])) | H5: =MAX(F5-(E5+G5),0) | I5: =MAX((E5+G5)-F5,0)
A6: =YEAR(TODAY()) | B6: 5 | C6: =TEXT(DATE(A6,B6,1),"mmmm") | D6: =SUMPRODUCT((IFERROR(--RIGHT(DailyRouteRecordTable[Departure Date],4),0)=A6)*(IFERROR(--MID(DailyRouteRecordTable[Departure Date],4,2),0)=B6)) | E6: =SUMPRODUCT((IFERROR(--RIGHT(DailyRouteRecordTable[Departure Date],4),0)=A6)*(IFERROR(--MID(DailyRouteRecordTable[Departure Date],4,2),0)=B6)*N(DailyRouteRecordTable[Total Expenses])) | F6: =SUMPRODUCT((IFERROR(--RIGHT(DailyRouteRecordTable[Departure Date],4),0)=A6)*(IFERROR(--MID(DailyRouteRecordTable[Departure Date],4,2),0)=B6)*N(DailyRouteRecordTable[Total Income])) | G6: =SUMPRODUCT((IFERROR(--RIGHT(DailyRouteRecordTable[Departure Date],4),0)=A6)*(IFERROR(--MID(DailyRouteRecordTable[Departure Date],4,2),0)=B6)*N(DailyRouteRecordTable[Additional Expense Amount])) | H6: =MAX(F6-(E6+G6),0) | I6: =MAX((E6+G6)-F6,0)
A7: =YEAR(TODAY()) | B7: 6 | C7: =TEXT(DATE(A7,B7,1),"mmmm") | D7: =SUMPRODUCT((IFERROR(--RIGHT(DailyRouteRecordTable[Departure Date],4),0)=A7)*(IFERROR(--MID(DailyRouteRecordTable[Departure Date],4,2),0)=B7)) | E7: =SUMPRODUCT((IFERROR(--RIGHT(DailyRouteRecordTable[Departure Date],4),0)=A7)*(IFERROR(--MID(DailyRouteRecordTable[Departure Date],4,2),0)=B7)*N(DailyRouteRecordTable[Total Expenses])) | F7: =SUMPRODUCT((IFERROR(--RIGHT(DailyRouteRecordTable[Departure Date],4),0)=A7)*(IFERROR(--MID(DailyRouteRecordTable[Departure Date],4,2),0)=B7)*N(DailyRouteRecordTable[Total Income])) | G7: =SUMPRODUCT((IFERROR(--RIGHT(DailyRouteRecordTable[Departure Date],4),0)=A7)*(IFERROR(--MID(DailyRouteRecordTable[Departure Date],4,2),0)=B7)*N(DailyRouteRecordTable[Additional Expense Amount])) | H7: =MAX(F7-(E7+G7),0) | I7: =MAX((E7+G7)-F7,0)
A8: =YEAR(TODAY()) | B8: 7 | C8: =TEXT(DATE(A8,B8,1),"mmmm") | D8: =SUMPRODUCT((IFERROR(--RIGHT(DailyRouteRecordTable[Departure Date],4),0)=A8)*(IFERROR(--MID(DailyRouteRecordTable[Departure Date],4,2),0)=B8)) | E8: =SUMPRODUCT((IFERROR(--RIGHT(DailyRouteRecordTable[Departure Date],4),0)=A8)*(IFERROR(--MID(DailyRouteRecordTable[Departure Date],4,2),0)=B8)*N(DailyRouteRecordTable[Total Expenses])) | F8: =SUMPRODUCT((IFERROR(--RIGHT(DailyRouteRecordTable[Departure Date],4),0)=A8)*(IFERROR(--MID(DailyRouteRecordTable[Departure Date],4,2),0)=B8)*N(DailyRouteRecordTable[Total Income])) | G8: =SUMPRODUCT((IFERROR(--RIGHT(DailyRouteRecordTable[Departure Date],4),0)=A8)*(IFERROR(--MID(DailyRouteRecordTable[Departure Date],4,2),0)=B8)*N(DailyRouteRecordTable[Additional Expense Amount])) | H8: =MAX(F8-(E8+G8),0) | I8: =MAX((E8+G8)-F8,0)
A9: =YEAR(TODAY()) | B9: 8 | C9: =TEXT(DATE(A9,B9,1),"mmmm") | D9: =SUMPRODUCT((IFERROR(--RIGHT(DailyRouteRecordTable[Departure Date],4),0)=A9)*(IFERROR(--MID(DailyRouteRecordTable[Departure Date],4,2),0)=B9)) | E9: =SUMPRODUCT((IFERROR(--RIGHT(DailyRouteRecordTable[Departure Date],4),0)=A9)*(IFERROR(--MID(DailyRouteRecordTable[Departure Date],4,2),0)=B9)*N(DailyRouteRecordTable[Total Expenses])) | F9: =SUMPRODUCT((IFERROR(--RIGHT(DailyRouteRecordTable[Departure Date],4),0)=A9)*(IFERROR(--MID(DailyRouteRecordTable[Departure Date],4,2),0)=B9)*N(DailyRouteRecordTable[Total Income])) | G9: =SUMPRODUCT((IFERROR(--RIGHT(DailyRouteRecordTable[Departure Date],4),0)=A9)*(IFERROR(--MID(DailyRouteRecordTable[Departure Date],4,2),0)=B9)*N(DailyRouteRecordTable[Additional Expense Amount])) | H9: =MAX(F9-(E9+G9),0) | I9: =MAX((E9+G9)-F9,0)
A10: =YEAR(TODAY()) | B10: 9 | C10: =TEXT(DATE(A10,B10,1),"mmmm") | D10: =SUMPRODUCT((IFERROR(--RIGHT(DailyRouteRecordTable[Departure Date],4),0)=A10)*(IFERROR(--MID(DailyRouteRecordTable[Departure Date],4,2),0)=B10)) | E10: =SUMPRODUCT((IFERROR(--RIGHT(DailyRouteRecordTable[Departure Date],4),0)=A10)*(IFERROR(--MID(DailyRouteRecordTable[Departure Date],4,2),0)=B10)*N(DailyRouteRecordTable[Total Expenses])) | F10: =SUMPRODUCT((IFERROR(--RIGHT(DailyRouteRecordTable[Departure Date],4),0)=A10)*(IFERROR(--MID(DailyRouteRecordTable[Departure Date],4,2),0)=B10)*N(DailyRouteRecordTable[Total Income])) | G10: =SUMPRODUCT((IFERROR(--RIGHT(DailyRouteRecordTable[Departure Date],4),0)=A10)*(IFERROR(--MID(DailyRouteRecordTable[Departure Date],4,2),0)=B10)*N(DailyRouteRecordTable[Additional Expense Amount])) | H10: =MAX(F10-(E10+G10),0) | I10: =MAX((E10+G10)-F10,0)
A11: =YEAR(TODAY()) | B11: 10 | C11: =TEXT(DATE(A11,B11,1),"mmmm") | D11: =SUMPRODUCT((IFERROR(--RIGHT(DailyRouteRecordTable[Departure Date],4),0)=A11)*(IFERROR(--MID(DailyRouteRecordTable[Departure Date],4,2),0)=B11)) | E11: =SUMPRODUCT((IFERROR(--RIGHT(DailyRouteRecordTable[Departure Date],4),0)=A11)*(IFERROR(--MID(DailyRouteRecordTable[Departure Date],4,2),0)=B11)*N(DailyRouteRecordTable[Total Expenses])) | F11: =SUMPRODUCT((IFERROR(--RIGHT(DailyRouteRecordTable[Departure Date],4),0)=A11)*(IFERROR(--MID(DailyRouteRecordTable[Departure Date],4,2),0)=B11)*N(DailyRouteRecordTable[Total Income])) | G11: =SUMPRODUCT((IFERROR(--RIGHT(DailyRouteRecordTable[Departure Date],4),0)=A11)*(IFERROR(--MID(DailyRouteRecordTable[Departure Date],4,2),0)=B11)*N(DailyRouteRecordTable[Additional Expense Amount])) | H11: =MAX(F11-(E11+G11),0) | I11: =MAX((E11+G11)-F11,0)
A12: =YEAR(TODAY()) | B12: 11 | C12: =TEXT(DATE(A12,B12,1),"mmmm") | D12: =SUMPRODUCT((IFERROR(--RIGHT(DailyRouteRecordTable[Departure Date],4),0)=A12)*(IFERROR(--MID(DailyRouteRecordTable[Departure Date],4,2),0)=B12)) | E12: =SUMPRODUCT((IFERROR(--RIGHT(DailyRouteRecordTable[Departure Date],4),0)=A12)*(IFERROR(--MID(DailyRouteRecordTable[Departure Date],4,2),0)=B12)*N(DailyRouteRecordTable[Total Expenses])) | F12: =SUMPRODUCT((IFERROR(--RIGHT(DailyRouteRecordTable[Departure Date],4),0)=A12)*(IFERROR(--MID(DailyRouteRecordTable[Departure Date],4,2),0)=B12)*N(DailyRouteRecordTable[Total Income])) | G12: =SUMPRODUCT((IFERROR(--RIGHT(DailyRouteRecordTable[Departure Date],4),0)=A12)*(IFERROR(--MID(DailyRouteRecordTable[Departure Date],4,2),0)=B12)*N(DailyRouteRecordTable[Additional Expense Amount])) | H12: =MAX(F12-(E12+G12),0) | I12: =MAX((E12+G12)-F12,0)
A13: =YEAR(TODAY()) | B13: 12 | C13: =TEXT(DATE(A13,B13,1),"mmmm") | D13: =SUMPRODUCT((IFERROR(--RIGHT(DailyRouteRecordTable[Departure Date],4),0)=A13)*(IFERROR(--MID(DailyRouteRecordTable[Departure Date],4,2),0)=B13)) | E13: =SUMPRODUCT((IFERROR(--RIGHT(DailyRouteRecordTable[Departure Date],4),0)=A13)*(IFERROR(--MID(DailyRouteRecordTable[Departure Date],4,2),0)=B13)*N(DailyRouteRecordTable[Total Expenses])) | F13: =SUMPRODUCT((IFERROR(--RIGHT(DailyRouteRecordTable[Departure Date],4),0)=A13)*(IFERROR(--MID(DailyRouteRecordTable[Departure Date],4,2),0)=B13)*N(DailyRouteRecordTable[Total Income])) | G13: =SUMPRODUCT((IFERROR(--RIGHT(DailyRouteRecordTable[Departure Date],4),0)=A13)*(IFERROR(--MID(DailyRouteRecordTable[Departure Date],4,2),0)=B13)*N(DailyRouteRecordTable[Additional Expense Amount])) | H13: =MAX(F13-(E13+G13),0) | I13: =MAX((E13+G13)-F13,0)

Sheet Yearly Summary
A1: Year | B1: Trips | C1: Total Expenses | D1: Total Income | E1: Additional Expenses | F1: Profit | G1: Loss
A2: =YEAR(TODAY())-4+ROW()-2 | B2: =SUMPRODUCT((IFERROR(--RIGHT(DailyRouteRecordTable[Departure Date],4),0)=A2)) | C2: =SUMPRODUCT((IFERROR(--RIGHT(DailyRouteRecordTable[Departure Date],4),0)=A2)*N(DailyRouteRecordTable[Total Expenses])) | D2: =SUMPRODUCT((IFERROR(--RIGHT(DailyRouteRecordTable[Departure Date],4),0)=A2)*N(DailyRouteRecordTable[Total Income])) | E2: =SUMPRODUCT((IFERROR(--RIGHT(DailyRouteRecordTable[Departure Date],4),0)=A2)*N(DailyRouteRecordTable[Additional Expense Amount])) | F2: =MAX(D2-(C2+E2),0) | G2: =MAX((C2+E2)-D2,0)
A3: =YEAR(TODAY())-4+ROW()-2 | B3: =SUMPRODUCT((IFERROR(--RIGHT(DailyRouteRecordTable[Departure Date],4),0)=A3)) | C3: =SUMPRODUCT((IFERROR(--RIGHT(DailyRouteRecordTable[Departure Date],4),0)=A3)*N(DailyRouteRecordTable[Total Expenses])) | D3: =SUMPRODUCT((IFERROR(--RIGHT(DailyRouteRecordTable[Departure Date],4),0)=A3)*N(DailyRouteRecordTable[Total Income])) | E3: =SUMPRODUCT((IFERROR(--RIGHT(DailyRouteRecordTable[Departure Date],4),0)=A3)*N(DailyRouteRecordTable[Additional Expense Amount])) | F3: =MAX(D3-(C3+E3),0) | G3: =MAX((C3+E3)-D3,0)
A4: =YEAR(TODAY())-4+ROW()-2 | B4: =SUMPRODUCT((IFERROR(--RIGHT(DailyRouteRecordTable[Departure Date],4),0)=A4)) | C4: =SUMPRODUCT((IFERROR(--RIGHT(DailyRouteRecordTable[Departure Date],4),0)=A4)*N(DailyRouteRecordTable[Total Expenses])) | D4: =SUMPRODUCT((IFERROR(--RIGHT(DailyRouteRecordTable[Departure Date],4),0)=A4)*N(DailyRouteRecordTable[Total Income])) | E4: =SUMPRODUCT((IFERROR(--RIGHT(DailyRouteRecordTable[Departure Date],4),0)=A4)*N(DailyRouteRecordTable[Additional Expense Amount])) | F4: =MAX(D4-(C4+E4),0) | G4: =MAX((C4+E4)-D4,0)
A5: =YEAR(TODAY())-4+ROW()-2 | B5: =SUMPRODUCT((IFERROR(--RIGHT(DailyRouteRecordTable[Departure Date],4),0)=A5)) | C5: =SUMPRODUCT((IFERROR(--RIGHT(DailyRouteRecordTable[Departure Date],4),0)=A5)*N(DailyRouteRecordTable[Total Expenses])) | D5: =SUMPRODUCT((IFERROR(--RIGHT(DailyRouteRecordTable[Departure Date],4),0)=A5)*N(DailyRouteRecordTable[Total Income])) | E5: =SUMPRODUCT((IFERROR(--RIGHT(DailyRouteRecordTable[Departure Date],4),0)=A5)*N(DailyRouteRecordTable[Additional Expense Amount])) | F5: =MAX(D5-(C5+E5),0) | G5: =MAX((C5+E5)-D5,0)
A6: =YEAR(TODAY())-4+ROW()-2 | B6: =SUMPRODUCT((IFERROR(--RIGHT(DailyRouteRecordTable[Departure Date],4),0)=A6)) | C6: =SUMPRODUCT((IFERROR(--RIGHT(DailyRouteRecordTable[Departure Date],4),0)=A6)*N(DailyRouteRecordTable[Total Expenses])) | D6: =SUMPRODUCT((IFERROR(--RIGHT(DailyRouteRecordTable[Departure Date],4),0)=A6)*N(DailyRouteRecordTable[Total Income])) | E6: =SUMPRODUCT((IFERROR(--RIGHT(DailyRouteRecordTable[Departure Date],4),0)=A6)*N(DailyRouteRecordTable[Additional Expense Amount])) | F6: =MAX(D6-(C6+E6),0) | G6: =MAX((C6+E6)-D6,0)
A7: =YEAR(TODAY())-4+ROW()-2 | B7: =SUMPRODUCT((IFERROR(--RIGHT(DailyRouteRecordTable[Departure Date],4),0)=A7)) | C7: =SUMPRODUCT((IFERROR(--RIGHT(DailyRouteRecordTable[Departure Date],4),0)=A7)*N(DailyRouteRecordTable[Total Expenses])) | D7: =SUMPRODUCT((IFERROR(--RIGHT(DailyRouteRecordTable[Departure Date],4),0)=A7)*N(DailyRouteRecordTable[Total Income])) | E7: =SUMPRODUCT((IFERROR(--RIGHT(DailyRouteRecordTable[Departure Date],4),0)=A7)*N(DailyRouteRecordTable[Additional Expense Amount])) | F7: =MAX(D7-(C7+E7),0) | G7: =MAX((C7+E7)-D7,0)
A8: =YEAR(TODAY())-4+ROW()-2 | B8: =SUMPRODUCT((IFERROR(--RIGHT(DailyRouteRecordTable[Departure Date],4),0)=A8)) | C8: =SUMPRODUCT((IFERROR(--RIGHT(DailyRouteRecordTable[Departure Date],4),0)=A8)*N(DailyRouteRecordTable[Total Expenses])) | D8: =SUMPRODUCT((IFERROR(--RIGHT(DailyRouteRecordTable[Departure Date],4),0)=A8)*N(DailyRouteRecordTable[Total Income])) | E8: =SUMPRODUCT((IFERROR(--RIGHT(DailyRouteRecordTable[Departure Date],4),0)=A8)*N(DailyRouteRecordTable[Additional Expense Amount])) | F8: =MAX(D8-(C8+E8),0) | G8: =MAX((C8+E8)-D8,0)
A9: =YEAR(TODAY())-4+ROW()-2 | B9: =SUMPRODUCT((IFERROR(--RIGHT(DailyRouteRecordTable[Departure Date],4),0)=A9)) | C9: =SUMPRODUCT((IFERROR(--RIGHT(DailyRouteRecordTable[Departure Date],4),0)=A9)*N(DailyRouteRecordTable[Total Expenses])) | D9: =SUMPRODUCT((IFERROR(--RIGHT(DailyRouteRecordTable[Departure Date],4),0)=A9)*N(DailyRouteRecordTable[Total Income])) | E9: =SUMPRODUCT((IFERROR(--RIGHT(DailyRouteRecordTable[Departure Date],4),0)=A9)*N(DailyRouteRecordTable[Additional Expense Amount])) | F9: =MAX(D9-(C9+E9),0) | G9: =MAX((C9+E9)-D9,0)
A10: =YEAR(TODAY())-4+ROW()-2 | B10: =SUMPRODUCT((IFERROR(--RIGHT(DailyRouteRecordTable[Departure Date],4),0)=A10)) | C10: =SUMPRODUCT((IFERROR(--RIGHT(DailyRouteRecordTable[Departure Date],4),0)=A10)*N(DailyRouteRecordTable[Total Expenses])) | D10: =SUMPRODUCT((IFERROR(--RIGHT(DailyRouteRecordTable[Departure Date],4),0)=A10)*N(DailyRouteRecordTable[Total Income])) | E10: =SUMPRODUCT((IFERROR(--RIGHT(DailyRouteRecordTable[Departure Date],4),0)=A10)*N(DailyRouteRecordTable[Additional Expense Amount])) | F10: =MAX(D10-(C10+E10),0) | G10: =MAX((C10+E10)-D10,0)
A11: =YEAR(TODAY())-4+ROW()-2 | B11: =SUMPRODUCT((IFERROR(--RIGHT(DailyRouteRecordTable[Departure Date],4),0)=A11)) | C11: =SUMPRODUCT((IFERROR(--RIGHT(DailyRouteRecordTable[Departure Date],4),0)=A11)*N(DailyRouteRecordTable[Total Expenses])) | D11: =SUMPRODUCT((IFERROR(--RIGHT(DailyRouteRecordTable[Departure Date],4),0)=A11)*N(DailyRouteRecordTable[Total Income])) | E11: =SUMPRODUCT((IFERROR(--RIGHT(DailyRouteRecordTable[Departure Date],4),0)=A11)*N(DailyRouteRecordTable[Additional Expense Amount])) | F11: =MAX(D11-(C11+E11),0) | G11: =MAX((C11+E11)-D11,0)

Sheet Dashboard
A1: Transport Business Dashboard | R1: Top 5 Profitable Routes | S1: Profit | T1: Top 5 Non-Profitable Routes | U1: Loss | AA1: Route Candidate | AB1: Route Profit | AC1: Route Loss | AD1: Profit Rank | AE1: Loss Rank
A2: Theme | B2: Light | R2: =IFERROR(INDEX($AA$2:$AA$501,MATCH(ROWS($R$2:R2),$AD$2:$AD$501,0)),"") | S2: =IF($R2="","",INDEX($AB$2:$AB$501,MATCH($R2,$AA$2:$AA$501,0))) | T2: =IFERROR(INDEX($AA$2:$AA$501,MATCH(ROWS($T$2:T2),$AE$2:$AE$501,0)),"") | U2: =IF($T2="","",INDEX($AC$2:$AC$501,MATCH($T2,$AA$2:$AA$501,0))) | AA2: =IFERROR(INDEX(DailyRouteRecordTable[Route],ROW()-1),"") | AB2: =IF(AA2="","",IF(COUNTIF($AA$2:AA2,AA2)>1,0,SUMPRODUCT((DailyRouteRecordTable[Route]=AA2)*(IF($B$6="All",1,IFERROR(--MID(DailyRouteRecordTable[Departure Date],4,2),0)=MATCH($B$6,{"January","February","March","April","May","June","July","August","September","October","November","December"},0)))*N(DailyRouteRecordTable[Profit])))) | AC2: =IF(AA2="","",IF(COUNTIF($AA$2:AA2,AA2)>1,0,SUMPRODUCT((DailyRouteRecordTable[Route]=AA2)*(IF($B$6="All",1,IFERROR(--MID(DailyRouteRecordTable[Departure Date],4,2),0)=MATCH($B$6,{"January","February","March","April","May","June","July","August","September","October","November","December"},0)))*N(DailyRouteRecordTable[Loss])))) | AD2: =IF(AB2<=0,"",RANK(AB2,$AB$2:$AB$501,0)+COUNTIFS($AB$2:AB2,AB2)-1) | AE2: =IF(AC2<=0,"",RANK(AC2,$AC$2:$AC$501,0)+COUNTIFS($AC$2:AC2,AC2)-1)
A3: Total Trips | C3: Total Income | E3: Total Expenses | G3: Total Profit | I3: Total Loss | K3: Net Result | R3: =IFERROR(INDEX($AA$2:$AA$501,MATCH(ROWS($R$2:R3),$AD$2:$AD$501,0)),"") | S3: =IF($R3="","",INDEX($AB$2:$AB$501,MATCH($R3,$AA$2:$AA$501,0))) | T3: =IFERROR(INDEX($AA$2:$AA$501,MATCH(ROWS($T$2:T3),$AE$2:$AE$501,0)),"") | U3: =IF($T3="","",INDEX($AC$2:$AC$501,MATCH($T3,$AA$2:$AA$501,0))) | AA3: =IFERROR(INDEX(DailyRouteRecordTable[Route],ROW()-1),"") | AB3: =IF(AA3="","",IF(COUNTIF($AA$2:AA3,AA3)>1,0,SUMPRODUCT((DailyRouteRecordTable[Route]=AA3)*(IF($B$6="All",1,IFERROR(--MID(DailyRouteRecordTable[Departure Date],4,2),0)=MATCH($B$6,{"January","February","March","April","May","June","July","August","September","October","November","December"},0)))*N(DailyRouteRecordTable[Profit])))) | AC3: =IF(AA3="","",IF(COUNTIF($AA$2:AA3,AA3)>1,0,SUMPRODUCT((DailyRouteRecordTable[Route]=AA3)*(IF($B$6="All",1,IFERROR(--MID(DailyRouteRecordTable[Departure Date],4,2),0)=MATCH($B$6,{"January","February","March","April","May","June","July","August","September","October","November","December"},0)))*N(DailyRouteRecordTable[Loss])))) | AD3: =IF(AB3<=0,"",RANK(AB3,$AB$2:$AB$501,0)+COUNTIFS($AB$2:AB3,AB3)-1) | AE3: =IF(AC3<=0,"",RANK(AC3,$AC$2:$AC$501,0)+COUNTIFS($AC$2:AC3,AC3)-1)
A4: =SUM('Monthly Summary'!D2:D13) | C4: =SUM('Monthly Summary'!F2:F13) | E4: =SUM('Monthly Summary'!E2:E13) | G4: =SUM('Monthly Summary'!H2:H13) | I4: =SUM('Monthly Summary'!I2:I13) | K4: =G4-I4 | R4: =IFERROR(INDEX($AA$2:$AA$501,MATCH(ROWS($R$2:R4),$AD$2:$AD$501,0)),"") | S4: =IF($R4="","",INDEX($AB$2:$AB$501,MATCH($R4,$AA$2:$AA$501,0))) | T4: =IFERROR(INDEX($AA$2:$AA$501,MATCH(ROWS($T$2:T4),$AE$2:$AE$501,0)),"") | U4: =IF($T4="","",INDEX($AC$2:$AC$501,MATCH($T4,$AA$2:$AA$501,0))) | AA4: =IFERROR(INDEX(DailyRouteRecordTable[Route],ROW()-1),"") | AB4: =IF(AA4="","",IF(COUNTIF($AA$2:AA4,AA4)>1,0,SUMPRODUCT((DailyRouteRecordTable[Route]=AA4)*(IF($B$6="All",1,IFERROR(--MID(DailyRouteRecordTable[Departure Date],4,2),0)=MATCH($B$6,{"January","February","March","April","May","June","July","August","September","October","November","December"},0)))*N(DailyRouteRecordTable[Profit])))) | AC4: =IF(AA4="","",IF(COUNTIF($AA$2:AA4,AA4)>1,0,SUMPRODUCT((DailyRouteRecordTable[Route]=AA4)*(IF($B$6="All",1,IFERROR(--MID(DailyRouteRecordTable[Departure Date],4,2),0)=MATCH($B$6,{"January","February","March","April","May","June","July","August","September","October","November","December"},0)))*N(DailyRouteRecordTable[Loss])))) | AD4: =IF(AB4<=0,"",RANK(AB4,$AB$2:$AB$501,0)+COUNTIFS($AB$2:AB4,AB4)-1) | AE4: =IF(AC4<=0,"",RANK(AC4,$AC$2:$AC$501,0)+COUNTIFS($AC$2:AC4,AC4)-1)
R5: =IFERROR(INDEX($AA$2:$AA$501,MATCH(ROWS($R$2:R5),$AD$2:$AD$501,0)),"") | S5: =IF($R5="","",INDEX($AB$2:$AB$501,MATCH($R5,$AA$2:$AA$501,0))) | T5: =IFERROR(INDEX($AA$2:$AA$501,MATCH(ROWS($T$2:T5),$AE$2:$AE$501,0)),"") | U5: =IF($T5="","",INDEX($AC$2:$AC$501,MATCH($T5,$AA$2:$AA$501,0))) | AA5: =IFERROR(INDEX(DailyRouteRecordTable[Route],ROW()-1),"") | AB5: =IF(AA5="","",IF(COUNTIF($AA$2:AA5,AA5)>1,0,SUMPRODUCT((DailyRouteRecordTable[Route]=AA5)*(IF($B$6="All",1,IFERROR(--MID(DailyRouteRecordTable[Departure Date],4,2),0)=MATCH($B$6,{"January","February","March","April","May","June","July","August","September","October","November","December"},0)))*N(DailyRouteRecordTable[Profit])))) | AC5: =IF(AA5="","",IF(COUNTIF($AA$2:AA5,AA5)>1,0,SUMPRODUCT((DailyRouteRecordTable[Route]=AA5)*(IF($B$6="All",1,IFERROR(--MID(DailyRouteRecordTable[Departure Date],4,2),0)=MATCH($B$6,{"January","February","March","April","May","June","July","August","September","October","November","December"},0)))*N(DailyRouteRecordTable[Loss])))) | AD5: =IF(AB5<=0,"",RANK(AB5,$AB$2:$AB$501,0)+COUNTIFS($AB$2:AB5,AB5)-1) | AE5: =IF(AC5<=0,"",RANK(AC5,$AC$2:$AC$501,0)+COUNTIFS($AC$2:AC5,AC5)-1)
A6: Month Selector | B6: All | C6: Pick month to update route-wise charts | R6: =IFERROR(INDEX($AA$2:$AA$501,MATCH(ROWS($R$2:R6),$AD$2:$AD$501,0)),"") | S6: =IF($R6="","",INDEX($AB$2:$AB$501,MATCH($R6,$AA$2:$AA$501,0))) | T6: =IFERROR(INDEX($AA$2:$AA$501,MATCH(ROWS($T$2:T6),$AE$2:$AE$501,0)),"") | U6: =IF($T6="","",INDEX($AC$2:$AC$501,MATCH($T6,$AA$2:$AA$501,0))) | AA6: =IFERROR(INDEX(DailyRouteRecordTable[Route],ROW()-1),"") | AB6: =IF(AA6="","",IF(COUNTIF($AA$2:AA6,AA6)>1,0,SUMPRODUCT((DailyRouteRecordTable[Route]=AA6)*(IF($B$6="All",1,IFERROR(--MID(DailyRouteRecordTable[Departure Date],4,2),0)=MATCH($B$6,{"January","February","March","April","May","June","July","August","September","October","November","December"},0)))*N(DailyRouteRecordTable[Profit])))) | AC6: =IF(AA6="","",IF(COUNTIF($AA$2:AA6,AA6)>1,0,SUMPRODUCT((DailyRouteRecordTable[Route]=AA6)*(IF($B$6="All",1,IFERROR(--MID(DailyRouteRecordTable[Departure Date],4,2),0)=MATCH($B$6,{"January","February","March","April","May","June","July","August","September","October","November","December"},0)))*N(DailyRouteRecordTable[Loss])))) | AD6: =IF(AB6<=0,"",RANK(AB6,$AB$2:$AB$501,0)+COUNTIFS($AB$2:AB6,AB6)-1) | AE6: =IF(AC6<=0,"",RANK(AC6,$AC$2:$AC$501,0)+COUNTIFS($AC$2:AC6,AC6)-1)
AA7: =IFERROR(INDEX(DailyRouteRecordTable[Route],ROW()-1),"") | AB7: =IF(AA7="","",IF(COUNTIF($AA$2:AA7,AA7)>1,0,SUMPRODUCT((DailyRouteRecordTable[Route]=AA7)*(IF($B$6="All",1,IFERROR(--MID(DailyRouteRecordTable[Departure Date],4,2),0)=MATCH($B$6,{"January","February","March","April","May","June","July","August","September","October","November","December"},0)))*N(DailyRouteRecordTable[Profit])))) | AC7: =IF(AA7="","",IF(COUNTIF($AA$2:AA7,AA7)>1,0,SUMPRODUCT((DailyRouteRecordTable[Route]=AA7)*(IF($B$6="All",1,IFERROR(--MID(DailyRouteRecordTable[Departure Date],4,2),0)=MATCH($B$6,{"January","February","March","April","May","June","July","August","September","October","November","December"},0)))*N(DailyRouteRecordTable[Loss])))) | AD7: =IF(AB7<=0,"",RANK(AB7,$AB$2:$AB$501,0)+COUNTIFS($AB$2:AB7,AB7)-1) | AE7: =IF(AC7<=0,"",RANK(AC7,$AC$2:$AC$501,0)+COUNTIFS($AC$2:AC7,AC7)-1)
AA8: =IFERROR(INDEX(DailyRouteRecordTable[Route],ROW()-1),"") | AB8: =IF(AA8="","",IF(COUNTIF($AA$2:AA8,AA8)>1,0,SUMPRODUCT((DailyRouteRecordTable[Route]=AA8)*(IF($B$6="All",1,IFERROR(--MID(DailyRouteRecordTable[Departure Date],4,2),0)=MATCH($B$6,{"January","February","March","April","May","June","July","August","September","October","November","December"},0)))*N(DailyRouteRecordTable[Profit])))) | AC8: =IF(AA8="","",IF(COUNTIF($AA$2:AA8,AA8)>1,0,SUMPRODUCT((DailyRouteRecordTable[Route]=AA8)*(IF($B$6="All",1,IFERROR(--MID(DailyRouteRecordTable[Departure Date],4,2),0)=MATCH($B$6,{"January","February","March","April","May","June","July","August","September","October","November","December"},0)))*N(DailyRouteRecordTable[Loss])))) | AD8: =IF(AB8<=0,"",RANK(AB8,$AB$2:$AB$501,0)+COUNTIFS($AB$2:AB8,AB8)-1) | AE8: =IF(AC8<=0,"",RANK(AC8,$AC$2:$AC$501,0)+COUNTIFS($AC$2:AC8,AC8)-1)
AA9: =IFERROR(INDEX(DailyRouteRecordTable[Route],ROW()-1),"") | AB9: =IF(AA9="","",IF(COUNTIF($AA$2:AA9,AA9)>1,0,SUMPRODUCT((DailyRouteRecordTable[Route]=AA9)*(IF($B$6="All",1,IFERROR(--MID(DailyRouteRecordTable[Departure Date],4,2),0)=MATCH($B$6,{"January","February","March","April","May","June","July","August","September","October","November","December"},0)))*N(DailyRouteRecordTable[Profit])))) | AC9: =IF(AA9="","",IF(COUNTIF($AA$2:AA9,AA9)>1,0,SUMPRODUCT((DailyRouteRecordTable[Route]=AA9)*(IF($B$6="All",1,IFERROR(--MID(DailyRouteRecordTable[Departure Date],4,2),0)=MATCH($B$6,{"January","February","March","April","May","June","July","August","September","October","November","December"},0)))*N(DailyRouteRecordTable[Loss])))) | AD9: =IF(AB9<=0,"",RANK(AB9,$AB$2:$AB$501,0)+COUNTIFS($AB$2:AB9,AB9)-1) | AE9: =IF(AC9<=0,"",RANK(AC9,$AC$2:$AC$501,0)+COUNTIFS($AC$2:AC9,AC9)-1)
AA10: =IFERROR(INDEX(DailyRouteRecordTable[Route],ROW()-1),"") | AB10: =IF(AA10="","",IF(COUNTIF($AA$2:AA10,AA10)>1,0,SUMPRODUCT((DailyRouteRecordTable[Route]=AA10)*(IF($B$6="All",1,IFERROR(--MID(DailyRouteRecordTable[Departure Date],4,2),0)=MATCH($B$6,{"January","February","March","April","May","June","July","August","September","October","November","December"},0)))*N(DailyRouteRecordTable[Profit])))) | AC10: =IF(AA10="","",IF(COUNTIF($AA$2:AA10,AA10)>1,0,SUMPRODUCT((DailyRouteRecordTable[Route]=AA10)*(IF($B$6="All",1,IFERROR(--MID(DailyRouteRecordTable[Departure Date],4,2),0)=MATCH($B$6,{"January","February","March","April","May","June","July","August","September","October","November","December"},0)))*N(DailyRouteRecordTable[Loss])))) | AD10: =IF(AB10<=0,"",RANK(AB10,$AB$2:$AB$501,0)+COUNTIFS($AB$2:AB10,AB10)-1) | AE10: =IF(AC10<=0,"",RANK(AC10,$AC$2:$AC$501,0)+COUNTIFS($AC$2:AC10,AC10)-1)
AA11: =IFERROR(INDEX(DailyRouteRecordTable[Route],ROW()-1),"") | AB11: =IF(AA11="","",IF(COUNTIF($AA$2:AA11,AA11)>1,0,SUMPRODUCT((DailyRouteRecordTable[Route]=AA11)*(IF($B$6="All",1,IFERROR(--MID(DailyRouteRecordTable[Departure Date],4,2),0)=MATCH($B$6,{"January","February","March","April","May","June","July","August","September","October","November","December"},0)))*N(DailyRouteRecordTable[Profit])))) | AC11: =IF(AA11="","",IF(COUNTIF($AA$2:AA11,AA11)>1,0,SUMPRODUCT((DailyRouteRecordTable[Route]=AA11)*(IF($B$6="All",1,IFERROR(--MID(DailyRouteRecordTable[Departure Date],4,2),0)=MATCH($B$6,{"January","February","March","April","May","June","July","August","September","October","November","December"},0)))*N(DailyRouteRecordTable[Loss])))) | AD11: =IF(AB11<=0,"",RANK(AB11,$AB$2:$AB$501,0)+COUNTIFS($AB$2:AB11,AB11)-1) | AE11: =IF(AC11<=0,"",RANK(AC11,$AC$2:$AC$501,0)+COUNTIFS($AC$2:AC11,AC11)-1)
AA12: =IFERROR(INDEX(DailyRouteRecordTable[Route],ROW()-1),"") | AB12: =IF(AA12="","",IF(COUNTIF($AA$2:AA12,AA12)>1,0,SUMPRODUCT((DailyRouteRecordTable[Route]=AA12)*(IF($B$6="All",1,IFERROR(--MID(DailyRouteRecordTable[Departure Date],4,2),0)=MATCH($B$6,{"January","February","March","April","May","June","July","August","September","October","November","December"},0)))*N(DailyRouteRecordTable[Profit])))) | AC12: =IF(AA12="","",IF(COUNTIF($AA$2:AA12,AA12)>1,0,SUMPRODUCT((DailyRouteRecordTable[Route]=AA12)*(IF($B$6="All",1,IFERROR(--MID(DailyRouteRecordTable[Departure Date],4,2),0)=MATCH($B$6,{"January","February","March","April","May","June","July","August","September","October","November","December"},0)))*N(DailyRouteRecordTable[Loss])))) | AD12: =IF(AB12<=0,"",RANK(AB12,$AB$2:$AB$501,0)+COUNTIFS($AB$2:AB12,AB12)-1) | AE12: =IF(AC12<=0,"",RANK(AC12,$AC$2:$AC$501,0)+COUNTIFS($AC$2:AC12,AC12)-1)
AA13: =IFERROR(INDEX(DailyRouteRecordTable[Route],ROW()-1),"") | AB13: =IF(AA13="","",IF(COUNTIF($AA$2:AA13,AA13)>1,0,SUMPRODUCT((DailyRouteRecordTable[Route]=AA13)*(IF($B$6="All",1,IFERROR(--MID(DailyRouteRecordTable[Departure Date],4,2),0)=MATCH($B$6,{"January","February","March","April","May","June","July","August","September","October","November","December"},0)))*N(DailyRouteRecordTable[Profit])))) | AC13: =IF(AA13="","",IF(COUNTIF($AA$2:AA13,AA13)>1,0,SUMPRODUCT((DailyRouteRecordTable[Route]=AA13)*(IF($B$6="All",1,IFERROR(--MID(DailyRouteRecordTable[Departure Date],4,2),0)=MATCH($B$6,{"January","February","March","April","May","June","July","August","September","October","November","December"},0)))*N(DailyRouteRecordTable[Loss])))) | AD13: =IF(AB13<=0,"",RANK(AB13,$AB$2:$AB$501,0)+COUNTIFS($AB$2:AB13,AB13)-1) | AE13: =IF(AC13<=0,"",RANK(AC13,$AC$2:$AC$501,0)+COUNTIFS($AC$2:AC13,AC13)-1)
AA14: =IFERROR(INDEX(DailyRouteRecordTable[Route],ROW()-1),"") | AB14: =IF(AA14="","",IF(COUNTIF($AA$2:AA14,AA14)>1,0,SUMPRODUCT((DailyRouteRecordTable[Route]=AA14)*(IF($B$6="All",1,IFERROR(--MID(DailyRouteRecordTable[Departure Date],4,2),0)=MATCH($B$6,{"January","February","March","April","May","June","July","August","September","October","November","December"},0)))*N(DailyRouteRecordTable[Profit])))) | AC14: =IF(AA14="","",IF(COUNTIF($AA$2:AA14,AA14)>1,0,SUMPRODUCT((DailyRouteRecordTable[Route]=AA14)*(IF($B$6="All",1,IFERROR(--MID(DailyRouteRecordTable[Departure Date],4,2),0)=MATCH($B$6,{"January","February","March","April","May","June","July","August","September","October","November","December"},0)))*N(DailyRouteRecordTable[Loss])))) | AD14: =IF(AB14<=0,"",RANK(AB14,$AB$2:$AB$501,0)+COUNTIFS($AB$2:AB14,AB14)-1) | AE14: =IF(AC14<=0,"",RANK(AC14,$AC$2:$AC$501,0)+COUNTIFS($AC$2:AC14,AC14)-1)
AA15: =IFERROR(INDEX(DailyRouteRecordTable[Route],ROW()-1),"") | AB15: =IF(AA15="","",IF(COUNTIF($AA$2:AA15,AA15)>1,0,SUMPRODUCT((DailyRouteRecordTable[Route]=AA15)*(IF($B$6="All",1,IFERROR(--MID(DailyRouteRecordTable[Departure Date],4,2),0)=MATCH($B$6,{"January","February","March","April","May","June","July","August","September","October","November","December"},0)))*N(DailyRouteRecordTable[Profit])))) | AC15: =IF(AA15="","",IF(COUNTIF($AA$2:AA15,AA15)>1,0,SUMPRODUCT((DailyRouteRecordTable[Route]=AA15)*(IF($B$6="All",1,IFERROR(--MID(DailyRouteRecordTable[Departure Date],4,2),0)=MATCH($B$6,{"January","February","March","April","May","June","July","August","September","October","November","December"},0)))*N(DailyRouteRecordTable[Loss])))) | AD15: =IF(AB15<=0,"",RANK(AB15,$AB$2:$AB$501,0)+COUNTIFS($AB$2:AB15,AB15)-1) | AE15: =IF(AC15<=0,"",RANK(AC15,$AC$2:$AC$501,0)+COUNTIFS($AC$2:AC15,AC15)-1)
AA16: =IFERROR(INDEX(DailyRouteRecordTable[Route],ROW()-1),"") | AB16: =IF(AA16="","",IF(COUNTIF($AA$2:AA16,AA16)>1,0,SUMPRODUCT((DailyRouteRecordTable[Route]=AA16)*(IF($B$6="All",1,IFERROR(--MID(DailyRouteRecordTable[Departure Date],4,2),0)=MATCH($B$6,{"January","February","March","April","May","June","July","August","September","October","November","December"},0)))*N(DailyRouteRecordTable[Profit])))) | AC16: =IF(AA16="","",IF(COUNTIF($AA$2:AA16,AA16)>1,0,SUMPRODUCT((DailyRouteRecordTable[Route]=AA16)*(IF($B$6="All",1,IFERROR(--MID(DailyRouteRecordTable[Departure Date],4,2),0)=MATCH($B$6,{"January","February","March","April","May","June","July","August","September","October","November","December"},0)))*N(DailyRouteRecordTable[Loss])))) | AD16: =IF(AB16<=0,"",RANK(AB16,$AB$2:$AB$501,0)+COUNTIFS($AB$2:AB16,AB16)-1) | AE16: =IF(AC16<=0,"",RANK(AC16,$AC$2:$AC$501,0)+COUNTIFS($AC$2:AC16,AC16)-1)
AA17: =IFERROR(INDEX(DailyRouteRecordTable[Route],ROW()-1),"") | AB17: =IF(AA17="","",IF(COUNTIF($AA$2:AA17,AA17)>1,0,SUMPRODUCT((DailyRouteRecordTable[Route]=AA17)*(IF($B$6="All",1,IFERROR(--MID(DailyRouteRecordTable[Departure Date],4,2),0)=MATCH($B$6,{"January","February","March","April","May","June","July","August","September","October","November","December"},0)))*N(DailyRouteRecordTable[Profit])))) | AC17: =IF(AA17="","",IF(COUNTIF($AA$2:AA17,AA17)>1,0,SUMPRODUCT((DailyRouteRecordTable[Route]=AA17)*(IF($B$6="All",1,IFERROR(--MID(DailyRouteRecordTable[Departure Date],4,2),0)=MATCH($B$6,{"January","February","March","April","May","June","July","August","September","October","November","December"},0)))*N(DailyRouteRecordTable[Loss])))) | AD17: =IF(AB17<=0,"",RANK(AB17,$AB$2:$AB$501,0)+COUNTIFS($AB$2:AB17,AB17)-1) | AE17: =IF(AC17<=0,"",RANK(AC17,$AC$2:$AC$501,0)+COUNTIFS($AC$2:AC17,AC17)-1)
AA18: =IFERROR(INDEX(DailyRouteRecordTable[Route],ROW()-1),"") | AB18: =IF(AA18="","",IF(COUNTIF($AA$2:AA18,AA18)>1,0,SUMPRODUCT((DailyRouteRecordTable[Route]=AA18)*(IF($B$6="All",1,IFERROR(--MID(DailyRouteRecordTable[Departure Date],4,2),0)=MATCH($B$6,{"January","February","March","April","May","June","July","August","September","October","November","December"},0)))*N(DailyRouteRecordTable[Profit])))) | AC18: =IF(AA18="","",IF(COUNTIF($AA$2:AA18,AA18)>1,0,SUMPRODUCT((DailyRouteRecordTable[Route]=AA18)*(IF($B$6="All",1,IFERROR(--MID(DailyRouteRecordTable[Departure Date],4,2),0)=MATCH($B$6,{"January","February","March","April","May","June","July","August","September","October","November","December"},0)))*N(DailyRouteRecordTable[Loss])))) | AD18: =IF(AB18<=0,"",RANK(AB18,$AB$2:$AB$501,0)+COUNTIFS($AB$2:AB18,AB18)-1) | AE18: =IF(AC18<=0,"",RANK(AC18,$AC$2:$AC$501,0)+COUNTIFS($AC$2:AC18,AC18)-1)
... AA501: =IFERROR(INDEX(DailyRouteRecordTable[Route],ROW()-1),"") | AB501: =IF(AA501="","",IF(COUNTIF($AA$2:AA501,AA501)>1,0,SUMPRODUCT((DailyRouteRecordTable[Route]=AA501)*(IF($B$6="All",1,IFERROR(--MID(DailyRouteRecordTable[Departure Date],4,2),0)=MATCH($B$6,{"January","February","March","April","May","June","July","August","September","October","November","December"},0)))*N(DailyRouteRecordTable[Profit])))) | AC501: =IF(AA501="","",IF(COUNTIF($AA$2:AA501,AA501)>1,0,SUMPRODUCT((DailyRouteRecordTable[Route]=AA501)*(IF($B$6="All",1,IFERROR(--MID(DailyRouteRecordTable[Departure Date],4,2),0)=MATCH($B$6,{"January","February","March","April","May","June","July","August","September","October","November","December"},0)))*N(DailyRouteRecordTable[Loss])))) | AD501: =IF(AB501<=0,"",RANK(AB501,$AB$2:$AB$501,0)+COUNTIFS($AB$2:AB501,AB501)-1) | AE501: =IF(AC501<=0,"",RANK(AC501,$AC$2:$AC$501,0)+COUNTIFS($AC$2:AC501,AC501)-1)
